amzsc/__init__.py
amzsc/handlers/__init__.py
amzsc/handlers/error_handler.py
amzsc/modules/driver/driver_amazon.py
amzsc/modules/driver/driver_config.py
amzsc/modules/driver/driver_manipulator.py
amzsc/modules/proxy/__init__.py
amzsc/modules/proxy/proxy.py
amzsc/modules/proxy/proxy_request.py
amzsc/scraper.py
amzsc/utils/__init__.py
amzsc/utils/constants.py
amzsc/utils/custom_types.py
amzsc/utils/file_worker.py
amzsc/utils/marketplace.py
amzsc-0.1.6.dist-info/WHEEL
amzsc-0.1.6.dist-info/METADATA
amzsc-0.1.6.dist-info/RECORD
