Metadata-Version: 2.3
Name: amzsc
Version: 0.1.6
Summary: Amazon product description scraper
License: MIT License
Classifier: License :: OSI Approved :: MIT License
Classifier: Programming Language :: Python
Classifier: Programming Language :: Python :: 3.10
Classifier: Programming Language :: Python :: 3.11
Classifier: Programming Language :: Python :: 3.12
Classifier: Programming Language :: Python :: 3.13
Classifier: Programming Language :: Python :: 3.14
Classifier: Programming Language :: Python :: 3 :: Only
Classifier: Topic :: Software Development :: Quality Assurance
Classifier: Topic :: Software Development :: Testing
Classifier: Topic :: Software Development :: Libraries
Requires-Dist: bs4>=0.0.2
Requires-Dist: fake-useragent>=2.2.0
Requires-Dist: requests>=2.32.5
Requires-Dist: selenium>=4.35.0
Requires-Python: >=3.10
